garpix_cart/CHANGELOG.md
garpix_cart/CONTRIBUTING.md
garpix_cart/MANIFEST.in
garpix_cart/README.md
garpix_cart/__init__.py
garpix_cart/abstracts.py
garpix_cart/apps.py
garpix_cart/exceptions.py
garpix_cart/mixins.py
garpix_cart/routers.py
garpix_cart/setup.py
garpix_cart/urls.py
garpix_cart/utils.py
garpix_cart/__pycache__/__init__.cpython-38.pyc
garpix_cart/__pycache__/apps.cpython-38.pyc
garpix_cart/__pycache__/mixins.cpython-38.pyc
garpix_cart/__pycache__/routers.cpython-38.pyc
garpix_cart/__pycache__/urls.cpython-38.pyc
garpix_cart/admin/__init__.py
garpix_cart/admin/cart.py
garpix_cart/admin/__pycache__/__init__.cpython-38.pyc
garpix_cart/admin/__pycache__/cart.cpython-38.pyc
garpix_cart/migrations/__init__.py
garpix_cart/migrations/__pycache__/__init__.cpython-38.pyc
garpix_cart/models/__init__.py
garpix_cart/models/cart.py
garpix_cart/models/__pycache__/__init__.cpython-38.pyc
garpix_cart/models/__pycache__/cart.cpython-38.pyc
garpix_cart/permissions/IsCustomer.py
garpix_cart/permissions/__init__.py
garpix_cart/permissions/__pycache__/IsCustomer.cpython-38.pyc
garpix_cart/permissions/__pycache__/__init__.cpython-38.pyc
garpix_cart/serializers/__init__.py
garpix_cart/serializers/cart.py
garpix_cart/serializers/__pycache__/__init__.cpython-38.pyc
garpix_cart/serializers/__pycache__/cart.cpython-38.pyc
garpix_cart/tests/__init__.py
garpix_cart/tests/test_api.py
garpix_cart/tests/__pycache__/__init__.cpython-38.pyc
garpix_cart/tests/__pycache__/test_api.cpython-38.pyc
garpix_cart/views/__init__.py
garpix_cart/views/cart.py
garpix_cart/views/__pycache__/__init__.cpython-38.pyc
garpix_cart/views/__pycache__/cart.cpython-38.pyc
garpix_cart-3.0.0.dist-info/METADATA
garpix_cart-3.0.0.dist-info/WHEEL
garpix_cart-3.0.0.dist-info/top_level.txt
garpix_cart-3.0.0.dist-info/RECORD
